quikey/__init__.py
quikey/autostart.py
quikey/directories.py
quikey/filewatch.py
quikey/importer.py
quikey/input.py
quikey/models.py
quikey/prompt.py
quikey/qkdaemon.py
quikey/quikey.py
quikey/version.py
quikey-0.1.5.dist-info/LICENSE
quikey-0.1.5.dist-info/METADATA
quikey-0.1.5.dist-info/WHEEL
quikey-0.1.5.dist-info/entry_points.txt
quikey-0.1.5.dist-info/top_level.txt
quikey-0.1.5.dist-info/RECORD
