Metadata-Version: 2.1
Name: quikey
Version: 0.1.5
Summary: A keyboard macro tool.
Home-page: https://github.com/bostrt/quikey
Author: bostrt
Author-email: UNKNOWN
License: UNKNOWN
Platform: UNKNOWN
Requires-Dist: click
Requires-Dist: python-daemon
Requires-Dist: inotify-simple
Requires-Dist: tinydb
Requires-Dist: pynput
Requires-Dist: terminaltables
Requires-Dist: pyxdg
Requires-Dist: humanize
Requires-Dist: pick
Requires-Dist: filelock
